xfetch/__init__.py
xfetch/cli.py
xfetch/core.py
xfetch-0.1.0.dist-info/licenses/LICENSE
xfetch-0.1.0.dist-info/METADATA
xfetch-0.1.0.dist-info/WHEEL
xfetch-0.1.0.dist-info/entry_points.txt
xfetch-0.1.0.dist-info/top_level.txt
xfetch-0.1.0.dist-info/RECORD
