Metadata-Version: 2.4
Name: xfetch
Version: 0.1.0
Summary: A neofetch-like system info tool for Windows
Author-email: Your Name <you@example.com>
License: MIT
Requires-Python: >=3.7
License-File: LICENSE
Dynamic: license-file
